{
    "modes": {
        "1": {
            "octave_name": "octave2",
            "octave_channel": 1
        },
        "2": {
            "octave_name": "octave1",
            "octave_channel": 2
        },
        "3": {
            "octave_name": "octave1",
            "octave_channel": 3
        },
        "4": {
            "octave_name": "octave1",
            "octave_channel": 1
        },
        "5": {
            "octave_name": "octave1",
            "octave_channel": 4
        },
        "6": {
            "octave_name": "octave2",
            "octave_channel": 2
        }
    },
    "lo_modes": {
        "1": {
            "mode_id": 1,
            "lo_freq": 7550000000,
            "gain": -10.0,
            "latest": 55
        },
        "2": {
            "mode_id": 2,
            "lo_freq": 4900000000.0,
            "gain": 0.0,
            "latest": 2
        },
        "3": {
            "mode_id": 3,
            "lo_freq": 4900000000.0,
            "gain": 0.0,
            "latest": 3
        },
        "4": {
            "mode_id": 4,
            "lo_freq": 5700000000.0,
            "gain": 10.0,
            "latest": 4
        },
        "5": {
            "mode_id": 5,
            "lo_freq": 6500000000.0,
            "gain": 0.0,
            "latest": 5
        },
        "6": {
            "mode_id": 6,
            "lo_freq": 6500000000.0,
            "gain": 0.0,
            "latest": 6
        },
        "7": {
            "mode_id": 2,
            "lo_freq": 4900000000.0,
            "gain": -10.0,
            "latest": 56
        },
        "8": {
            "mode_id": 3,
            "lo_freq": 4900000000.0,
            "gain": -10.0,
            "latest": 57
        },
        "9": {
            "mode_id": 4,
            "lo_freq": 5700000000.0,
            "gain": -10.0,
            "latest": 58
        },
        "10": {
            "mode_id": 5,
            "lo_freq": 6500000000.0,
            "gain": -10.0,
            "latest": 59
        },
        "11": {
            "mode_id": 6,
            "lo_freq": 6500000000.0,
            "gain": -10.0,
            "latest": 60
        },
        "12": {
            "mode_id": 2,
            "lo_freq": 4850000000.0,
            "gain": -10.0,
            "latest": 44
        },
        "13": {
            "mode_id": 3,
            "lo_freq": 4850000000.0,
            "gain": -10.0,
            "latest": 45
        }
    },
    "lo_cal": {
        "1": {
            "i0": 0.028035942286506004,
            "q0": -0.011708914390044834,
            "lo_mode_id": 1,
            "dc_gain": -0.009313484151859064,
            "dc_phase": -0.06368649341472403,
            "temperature": 58.4375,
            "timestamp": 1728555011.621872,
            "method": "auto"
        },
        "2": {
            "i0": 0.029510097944361643,
            "q0": 0.036725028044282876,
            "lo_mode_id": 2,
            "dc_gain": 0.007719351683952436,
            "dc_phase": 0.18816069115761117,
            "temperature": 59.5,
            "timestamp": 1728555085.447531,
            "method": "auto"
        },
        "3": {
            "i0": 0.01619254948976476,
            "q0": 0.028254306787719285,
            "lo_mode_id": 3,
            "dc_gain": 0.008744561896323555,
            "dc_phase": 0.191184613028981,
            "temperature": 54.875,
            "timestamp": 1728555102.247863,
            "method": "auto"
        },
        "4": {
            "i0": 0.023456555963836914,
            "q0": 0.01565339486414088,
            "lo_mode_id": 4,
            "dc_gain": -0.013359137024201329,
            "dc_phase": 0.008028908432863973,
            "temperature": 53.375,
            "timestamp": 1728555120.413349,
            "method": "auto"
        },
        "5": {
            "i0": -0.012202128170599371,
            "q0": 0.028255144518542448,
            "lo_mode_id": 5,
            "dc_gain": 0.0021085284346242794,
            "dc_phase": -0.0733929539473496,
            "temperature": 51.0,
            "timestamp": 1728555137.2554877,
            "method": "auto"
        },
        "6": {
            "i0": 0.012486785234290233,
            "q0": 0.015738148611967977,
            "lo_mode_id": 6,
            "dc_gain": -0.0018810260208055318,
            "dc_phase": -0.08192374494394078,
            "temperature": 56.0625,
            "timestamp": 1728555154.7899745,
            "method": "auto"
        },
        "7": {
            "i0": 0.027707354597597655,
            "q0": -0.011946006906504963,
            "lo_mode_id": 1,
            "dc_gain": -0.009489001404959452,
            "dc_phase": -0.06341541784689847,
            "temperature": 58.1875,
            "timestamp": 1735648177.9167316,
            "method": "auto"
        },
        "8": {
            "i0": 0.028155119210069697,
            "q0": 0.03571694770822562,
            "lo_mode_id": 7,
            "dc_gain": 0.007038535883377772,
            "dc_phase": 0.18705448531238944,
            "temperature": 59.1875,
            "timestamp": 1735648190.2755551,
            "method": "auto"
        },
        "9": {
            "i0": 0.01655695240264618,
            "q0": 0.028054559851674134,
            "lo_mode_id": 8,
            "dc_gain": 0.008632931762315277,
            "dc_phase": 0.19015226486767864,
            "temperature": 54.5,
            "timestamp": 1735648202.6614616,
            "method": "auto"
        },
        "10": {
            "i0": 0.023580199328885634,
            "q0": 0.0161723542205615,
            "lo_mode_id": 9,
            "dc_gain": -0.0083021134923138,
            "dc_phase": 0.01962877380661067,
            "temperature": 52.6875,
            "timestamp": 1735648215.912375,
            "method": "auto"
        },
        "11": {
            "i0": -0.012161505234274282,
            "q0": 0.0278598463895106,
            "lo_mode_id": 10,
            "dc_gain": 0.001956778163086703,
            "dc_phase": -0.07091655449083395,
            "temperature": 50.5625,
            "timestamp": 1735648228.8040519,
            "method": "auto"
        },
        "12": {
            "i0": 0.0128394687380377,
            "q0": 0.015228448746422195,
            "lo_mode_id": 11,
            "dc_gain": -0.00267141291146189,
            "dc_phase": -0.07967125297738856,
            "temperature": 55.8125,
            "timestamp": 1735648241.1943805,
            "method": "auto"
        },
        "13": {
            "i0": 0.02779637209982669,
            "q0": -0.011837482412834851,
            "lo_mode_id": 1,
            "dc_gain": -0.009420633106119292,
            "dc_phase": -0.06318486095879296,
            "temperature": 58.25,
            "timestamp": 1735803667.4964356,
            "method": "auto"
        },
        "14": {
            "i0": 0.02822892282573377,
            "q0": 0.035751200438803844,
            "lo_mode_id": 7,
            "dc_gain": 0.007683351546615924,
            "dc_phase": 0.1872707352388064,
            "temperature": 59.25,
            "timestamp": 1735803679.759929,
            "method": "auto"
        },
        "15": {
            "i0": 0.016508977808720945,
            "q0": 0.028178782937917198,
            "lo_mode_id": 8,
            "dc_gain": 0.00803682479120571,
            "dc_phase": 0.18995148625038086,
            "temperature": 54.5625,
            "timestamp": 1735803690.3476005,
            "method": "auto"
        },
        "16": {
            "i0": 0.023666902160879428,
            "q0": 0.016168138142478642,
            "lo_mode_id": 9,
            "dc_gain": -0.007964038016524344,
            "dc_phase": 0.019601966455126716,
            "temperature": 52.875,
            "timestamp": 1735803702.2803957,
            "method": "auto"
        },
        "17": {
            "i0": -0.012100251226113874,
            "q0": 0.027871835128761194,
            "lo_mode_id": 10,
            "dc_gain": 0.0017748739322334117,
            "dc_phase": -0.07105179242785926,
            "temperature": 50.625,
            "timestamp": 1735803714.316382,
            "method": "auto"
        },
        "18": {
            "i0": 0.012869463522358186,
            "q0": 0.015265286518063664,
            "lo_mode_id": 11,
            "dc_gain": -0.002454330710652486,
            "dc_phase": -0.07970260114278549,
            "temperature": 55.9375,
            "timestamp": 1735803726.8336794,
            "method": "auto"
        },
        "19": {
            "i0": 0.027833227477623748,
            "q0": -0.011764157368405196,
            "lo_mode_id": 1,
            "dc_gain": -0.009371921250275306,
            "dc_phase": -0.06317634798037118,
            "temperature": 58.375,
            "timestamp": 1736755867.2860136,
            "method": "auto"
        },
        "20": {
            "i0": 0.028244862920949652,
            "q0": 0.035745636415264216,
            "lo_mode_id": 7,
            "dc_gain": 0.007662522508659508,
            "dc_phase": 0.1872177303223821,
            "temperature": 59.3125,
            "timestamp": 1736755879.5400736,
            "method": "auto"
        },
        "21": {
            "i0": 0.016501235817186235,
            "q0": 0.02813868517343207,
            "lo_mode_id": 8,
            "dc_gain": 0.008355345833761518,
            "dc_phase": 0.19003954107410023,
            "temperature": 54.75,
            "timestamp": 1736755891.1805177,
            "method": "auto"
        },
        "22": {
            "i0": 0.023667393508350277,
            "q0": 0.016185192797596334,
            "lo_mode_id": 9,
            "dc_gain": -0.0078700435558543,
            "dc_phase": 0.020053843272091053,
            "temperature": 53.0,
            "timestamp": 1736755903.8133752,
            "method": "auto"
        },
        "23": {
            "i0": -0.012102595199550098,
            "q0": 0.02786350832434291,
            "lo_mode_id": 10,
            "dc_gain": 0.0017072048319479727,
            "dc_phase": -0.07080344588803522,
            "temperature": 50.8125,
            "timestamp": 1736755915.5829737,
            "method": "auto"
        },
        "24": {
            "i0": 0.012932458595075039,
            "q0": 0.015262967952907889,
            "lo_mode_id": 11,
            "dc_gain": -0.0027248159748868295,
            "dc_phase": -0.07954882947347264,
            "temperature": 56.0625,
            "timestamp": 1736755927.397988,
            "method": "auto"
        },
        "25": {
            "i0": 0.02786030595366685,
            "q0": -0.01174006356017017,
            "lo_mode_id": 1,
            "dc_gain": -0.008944298825114716,
            "dc_phase": -0.06288566586417618,
            "temperature": 58.375,
            "timestamp": 1736756013.4797325,
            "method": "auto"
        },
        "26": {
            "i0": 0.028224428439390242,
            "q0": 0.035748593824382016,
            "lo_mode_id": 7,
            "dc_gain": 0.007458803755047594,
            "dc_phase": 0.18713261086194838,
            "temperature": 59.3125,
            "timestamp": 1736756025.2559524,
            "method": "auto"
        },
        "27": {
            "i0": 0.016509578664049944,
            "q0": 0.028130328122719872,
            "lo_mode_id": 8,
            "dc_gain": 0.00869083011666505,
            "dc_phase": 0.19035810310562418,
            "temperature": 54.75,
            "timestamp": 1736756037.1688855,
            "method": "auto"
        },
        "28": {
            "i0": 0.02367928409076158,
            "q0": 0.016184607830396193,
            "lo_mode_id": 9,
            "dc_gain": -0.008219425378671485,
            "dc_phase": 0.020031027597934393,
            "temperature": 53.0625,
            "timestamp": 1736756049.2876968,
            "method": "auto"
        },
        "29": {
            "i0": -0.012113445461497148,
            "q0": 0.027882597533100458,
            "lo_mode_id": 10,
            "dc_gain": 0.0016494899653711759,
            "dc_phase": -0.07074350686753096,
            "temperature": 50.75,
            "timestamp": 1736756061.9104617,
            "method": "auto"
        },
        "30": {
            "i0": 0.012932757373691867,
            "q0": 0.015255259668812539,
            "lo_mode_id": 11,
            "dc_gain": -0.0026156769148544257,
            "dc_phase": -0.07923771711062634,
            "temperature": 56.0625,
            "timestamp": 1736756075.1094818,
            "method": "auto"
        },
        "31": {
            "i0": 0.02772320264677517,
            "q0": -0.011731106993902195,
            "lo_mode_id": 1,
            "dc_gain": -0.009129920786037804,
            "dc_phase": -0.06354207813826368,
            "temperature": 58.4375,
            "timestamp": 1738929787.9595284,
            "method": "auto"
        },
        "32": {
            "i0": 0.028141015028757637,
            "q0": 0.03603303094798,
            "lo_mode_id": 7,
            "dc_gain": 0.007187210552838552,
            "dc_phase": 0.18740716920494058,
            "temperature": 59.375,
            "timestamp": 1738929800.5711176,
            "method": "auto"
        },
        "33": {
            "i0": 0.01669410806687037,
            "q0": 0.028184825563842247,
            "lo_mode_id": 8,
            "dc_gain": 0.008631740589218673,
            "dc_phase": 0.19046401195941193,
            "temperature": 54.875,
            "timestamp": 1738929813.0873144,
            "method": "auto"
        },
        "34": {
            "i0": 0.023672643310876852,
            "q0": 0.016133484864821475,
            "lo_mode_id": 9,
            "dc_gain": -0.0073866341054443785,
            "dc_phase": 0.02042465703363759,
            "temperature": 53.0,
            "timestamp": 1738929825.7454808,
            "method": "auto"
        },
        "35": {
            "i0": -0.012197722887241438,
            "q0": 0.027823128671270018,
            "lo_mode_id": 10,
            "dc_gain": 0.001412580774488914,
            "dc_phase": -0.07058045790431308,
            "temperature": 50.9375,
            "timestamp": 1738929838.6743612,
            "method": "auto"
        },
        "36": {
            "i0": 0.012785333148056686,
            "q0": 0.015398474046101354,
            "lo_mode_id": 11,
            "dc_gain": -0.0023115538496916166,
            "dc_phase": -0.07914078386840093,
            "temperature": 56.125,
            "timestamp": 1738929851.3108902,
            "method": "auto"
        },
        "37": {
            "i0": 0.02776340958914836,
            "q0": -0.011757601576508377,
            "lo_mode_id": 1,
            "dc_gain": -0.009128218242770658,
            "dc_phase": -0.0632743952164706,
            "temperature": 58.75,
            "timestamp": 1739797483.1366208,
            "method": "auto"
        },
        "38": {
            "i0": 0.02824655128990789,
            "q0": 0.035833414502509806,
            "lo_mode_id": 7,
            "dc_gain": 0.007545661931943837,
            "dc_phase": 0.1872370077550059,
            "temperature": 59.5,
            "timestamp": 1739797495.2115738,
            "method": "auto"
        },
        "39": {
            "i0": 0.01668458412486446,
            "q0": 0.02835376684170378,
            "lo_mode_id": 8,
            "dc_gain": 0.00817955272584081,
            "dc_phase": 0.19035508872473028,
            "temperature": 55.125,
            "timestamp": 1739797508.2036755,
            "method": "auto"
        },
        "40": {
            "i0": 0.023730171212450545,
            "q0": 0.016099032153199598,
            "lo_mode_id": 9,
            "dc_gain": -0.007901873049545927,
            "dc_phase": 0.020576932035694797,
            "temperature": 53.1875,
            "timestamp": 1739797520.5104797,
            "method": "auto"
        },
        "41": {
            "i0": -0.012199457075650877,
            "q0": 0.02790477848609333,
            "lo_mode_id": 10,
            "dc_gain": 0.0014830655565762907,
            "dc_phase": -0.07047531053385717,
            "temperature": 51.25,
            "timestamp": 1739797533.5035336,
            "method": "auto"
        },
        "42": {
            "i0": 0.012777645649598416,
            "q0": 0.015394694079814628,
            "lo_mode_id": 11,
            "dc_gain": -0.002650025817738766,
            "dc_phase": -0.07922313062308546,
            "temperature": 56.5625,
            "timestamp": 1739797546.1642473,
            "method": "auto"
        },
        "43": {
            "i0": 0.003557407182962911,
            "q0": 0.005542000139598562,
            "lo_mode_id": 1,
            "dc_gain": -0.003920791090819997,
            "dc_phase": -0.08858268780654875,
            "temperature": 58.9375,
            "timestamp": 1741767943.1037655,
            "method": "auto"
        },
        "44": {
            "i0": 0.009005113901847783,
            "q0": 0.007094875122410993,
            "lo_mode_id": 12,
            "dc_gain": 0.012963826302784476,
            "dc_phase": 0.17280721616731748,
            "temperature": 58.625,
            "timestamp": 1741767955.625932,
            "method": "auto"
        },
        "45": {
            "i0": 0.009881953560705115,
            "q0": 0.040844140555189916,
            "lo_mode_id": 13,
            "dc_gain": 0.015723183473236535,
            "dc_phase": 0.1768231080600436,
            "temperature": 59.375,
            "timestamp": 1741767968.188409,
            "method": "auto"
        },
        "46": {
            "i0": 0.001830209314264376,
            "q0": 0.02250312395670818,
            "lo_mode_id": 9,
            "dc_gain": -0.006682464249325726,
            "dc_phase": 0.012635284240770484,
            "temperature": 53.25,
            "timestamp": 1741767980.482329,
            "method": "auto"
        },
        "47": {
            "i0": 0.008725386011861456,
            "q0": 0.019532541443216134,
            "lo_mode_id": 10,
            "dc_gain": 0.002130875478544958,
            "dc_phase": -0.07272066948918107,
            "temperature": 56.0,
            "timestamp": 1741767993.1163359,
            "method": "auto"
        },
        "48": {
            "i0": 0.017741523034368885,
            "q0": 0.02859392705401085,
            "lo_mode_id": 11,
            "dc_gain": 0.003041194520131185,
            "dc_phase": -0.07687164288103736,
            "temperature": 55.375,
            "timestamp": 1741768006.2221165,
            "method": "auto"
        },
        "49": {
            "i0": 0.00362363119561887,
            "q0": 0.005678840320837521,
            "lo_mode_id": 1,
            "dc_gain": -0.0037534123608385928,
            "dc_phase": -0.08796877859637364,
            "temperature": 57.9375,
            "timestamp": 1742194229.546349,
            "method": "auto"
        },
        "50": {
            "i0": 0.004936295240894936,
            "q0": 0.004872168737429769,
            "lo_mode_id": 7,
            "dc_gain": 0.012395148417577717,
            "dc_phase": 0.1783536235606681,
            "temperature": 58.3125,
            "timestamp": 1742194241.7323604,
            "method": "auto"
        },
        "51": {
            "i0": 0.006431156885472388,
            "q0": 0.04097394183984774,
            "lo_mode_id": 8,
            "dc_gain": 0.014692685002958283,
            "dc_phase": 0.18739382331532645,
            "temperature": 59.3125,
            "timestamp": 1742194254.674819,
            "method": "auto"
        },
        "52": {
            "i0": 0.0017194331858098747,
            "q0": 0.022332451216915336,
            "lo_mode_id": 9,
            "dc_gain": -0.00675265738108044,
            "dc_phase": 0.013122472691251661,
            "temperature": 52.8125,
            "timestamp": 1742194267.7436032,
            "method": "auto"
        },
        "53": {
            "i0": 0.00883721149430158,
            "q0": 0.01936559686734329,
            "lo_mode_id": 10,
            "dc_gain": 0.002275005845177702,
            "dc_phase": -0.07261616189631181,
            "temperature": 56.0625,
            "timestamp": 1742194280.063001,
            "method": "auto"
        },
        "54": {
            "i0": 0.017980116631239815,
            "q0": 0.028642136106989777,
            "lo_mode_id": 11,
            "dc_gain": 0.0027298428369539884,
            "dc_phase": -0.07700057173400857,
            "temperature": 52.5,
            "timestamp": 1742194292.6128235,
            "method": "auto"
        },
        "55": {
            "i0": 0.0036228647017093984,
            "q0": 0.005729426391910004,
            "lo_mode_id": 1,
            "dc_gain": -0.004044668049407618,
            "dc_phase": -0.08784372229150297,
            "temperature": 58.0625,
            "timestamp": 1742278003.8364124,
            "method": "auto"
        },
        "56": {
            "i0": 0.004983895604116668,
            "q0": 0.004877999122418426,
            "lo_mode_id": 7,
            "dc_gain": 0.012894359512170883,
            "dc_phase": 0.17854803209578338,
            "temperature": 58.375,
            "timestamp": 1742278016.6882675,
            "method": "auto"
        },
        "57": {
            "i0": 0.006450578349713729,
            "q0": 0.040984077841798326,
            "lo_mode_id": 8,
            "dc_gain": 0.015223059667321293,
            "dc_phase": 0.18781402909255246,
            "temperature": 59.375,
            "timestamp": 1742278029.27619,
            "method": "auto"
        },
        "58": {
            "i0": 0.001743043808782493,
            "q0": 0.02231399988845243,
            "lo_mode_id": 9,
            "dc_gain": -0.006509984168391658,
            "dc_phase": 0.013211283193105782,
            "temperature": 52.875,
            "timestamp": 1742278042.2771,
            "method": "auto"
        },
        "59": {
            "i0": 0.008826378201847366,
            "q0": 0.019392553639423854,
            "lo_mode_id": 10,
            "dc_gain": 0.001897252114600123,
            "dc_phase": -0.07237936319632499,
            "temperature": 56.0625,
            "timestamp": 1742278055.4567258,
            "method": "auto"
        },
        "60": {
            "i0": 0.018038312080128176,
            "q0": 0.028653526013233444,
            "lo_mode_id": 11,
            "dc_gain": 0.0032091266231095705,
            "dc_phase": -0.07684225599728248,
            "temperature": 52.625,
            "timestamp": 1742278069.1405792,
            "method": "auto"
        }
    },
    "if_modes": {
        "1": {
            "lo_mode_id": 1,
            "if_freq": -347551064,
            "latest": 1
        },
        "2": {
            "lo_mode_id": 1,
            "if_freq": -217665199,
            "latest": 2
        },
        "3": {
            "lo_mode_id": 1,
            "if_freq": -56795338,
            "latest": 3
        },
        "4": {
            "lo_mode_id": 1,
            "if_freq": 110383000,
            "latest": 4
        },
        "5": {
            "lo_mode_id": 1,
            "if_freq": 243718235,
            "latest": 5
        },
        "6": {
            "lo_mode_id": 2,
            "if_freq": -126598153.0,
            "latest": 6
        },
        "7": {
            "lo_mode_id": 3,
            "if_freq": -91615606.0,
            "latest": 7
        },
        "8": {
            "lo_mode_id": 4,
            "if_freq": -187828514.0,
            "latest": 8
        },
        "9": {
            "lo_mode_id": 5,
            "if_freq": -170703765.0,
            "latest": 9
        },
        "10": {
            "lo_mode_id": 6,
            "if_freq": -263774100.0,
            "latest": 10
        },
        "11": {
            "lo_mode_id": 1,
            "if_freq": -347039175,
            "latest": 11
        },
        "12": {
            "lo_mode_id": 1,
            "if_freq": -213849961,
            "latest": 12
        },
        "13": {
            "lo_mode_id": 1,
            "if_freq": -54049898,
            "latest": 13
        },
        "14": {
            "lo_mode_id": 1,
            "if_freq": 110665282,
            "latest": 14
        },
        "15": {
            "lo_mode_id": 1,
            "if_freq": 243584062,
            "latest": 15
        },
        "16": {
            "lo_mode_id": 7,
            "if_freq": -131989341.0,
            "latest": 16
        },
        "17": {
            "lo_mode_id": 8,
            "if_freq": -86659729.0,
            "latest": 17
        },
        "18": {
            "lo_mode_id": 9,
            "if_freq": -182332044.0,
            "latest": 18
        },
        "19": {
            "lo_mode_id": 10,
            "if_freq": -167151952.0,
            "latest": 19
        },
        "20": {
            "lo_mode_id": 11,
            "if_freq": -260548143.0,
            "latest": 20
        },
        "21": {
            "lo_mode_id": 1,
            "if_freq": -346815320,
            "latest": 21
        },
        "22": {
            "lo_mode_id": 1,
            "if_freq": -213746900,
            "latest": 22
        },
        "23": {
            "lo_mode_id": 1,
            "if_freq": -53817110,
            "latest": 23
        },
        "24": {
            "lo_mode_id": 1,
            "if_freq": 111115741,
            "latest": 24
        },
        "25": {
            "lo_mode_id": 1,
            "if_freq": 243876637,
            "latest": 25
        },
        "26": {
            "lo_mode_id": 7,
            "if_freq": -131988940.0,
            "latest": 26
        },
        "27": {
            "lo_mode_id": 8,
            "if_freq": -86625975.0,
            "latest": 27
        },
        "28": {
            "lo_mode_id": 9,
            "if_freq": -182333477.0,
            "latest": 28
        },
        "29": {
            "lo_mode_id": 10,
            "if_freq": -167134510.0,
            "latest": 29
        },
        "30": {
            "lo_mode_id": 11,
            "if_freq": -260817859.0,
            "latest": 30
        },
        "31": {
            "lo_mode_id": 1,
            "if_freq": -346809717,
            "latest": 41
        },
        "32": {
            "lo_mode_id": 1,
            "if_freq": -213767913,
            "latest": 42
        },
        "33": {
            "lo_mode_id": 1,
            "if_freq": -53860440,
            "latest": 43
        },
        "34": {
            "lo_mode_id": 1,
            "if_freq": 111109396,
            "latest": 44
        },
        "35": {
            "lo_mode_id": 1,
            "if_freq": 243859220,
            "latest": 45
        },
        "36": {
            "lo_mode_id": 7,
            "if_freq": -131805000.0,
            "latest": 46
        },
        "37": {
            "lo_mode_id": 8,
            "if_freq": -86503379.0,
            "latest": 47
        },
        "38": {
            "lo_mode_id": 9,
            "if_freq": -181940382.0,
            "latest": 48
        },
        "39": {
            "lo_mode_id": 10,
            "if_freq": -168002393.0,
            "latest": 49
        },
        "40": {
            "lo_mode_id": 11,
            "if_freq": -260726690.0,
            "latest": 50
        },
        "41": {
            "lo_mode_id": 1,
            "if_freq": -347115353,
            "latest": 61
        },
        "42": {
            "lo_mode_id": 1,
            "if_freq": -214039190,
            "latest": 62
        },
        "43": {
            "lo_mode_id": 1,
            "if_freq": -54049691,
            "latest": 63
        },
        "44": {
            "lo_mode_id": 1,
            "if_freq": 110671227,
            "latest": 64
        },
        "45": {
            "lo_mode_id": 1,
            "if_freq": 243434067,
            "latest": 65
        },
        "46": {
            "lo_mode_id": 7,
            "if_freq": -131731875.0,
            "latest": 66
        },
        "47": {
            "lo_mode_id": 8,
            "if_freq": -86411572.0,
            "latest": 67
        },
        "48": {
            "lo_mode_id": 9,
            "if_freq": -181961023.0,
            "latest": 68
        },
        "49": {
            "lo_mode_id": 10,
            "if_freq": -167919400.0,
            "latest": 69
        },
        "50": {
            "lo_mode_id": 11,
            "if_freq": -260803178.0,
            "latest": 70
        },
        "51": {
            "lo_mode_id": 1,
            "if_freq": -347202421,
            "latest": 81
        },
        "52": {
            "lo_mode_id": 1,
            "if_freq": -214319630,
            "latest": 92
        },
        "53": {
            "lo_mode_id": 1,
            "if_freq": -54172276,
            "latest": 93
        },
        "54": {
            "lo_mode_id": 1,
            "if_freq": 110581126,
            "latest": 84
        },
        "55": {
            "lo_mode_id": 1,
            "if_freq": 243642218,
            "latest": 95
        },
        "56": {
            "lo_mode_id": 12,
            "if_freq": -81770699.0,
            "latest": 76
        },
        "57": {
            "lo_mode_id": 13,
            "if_freq": -36467904.0,
            "latest": 77
        },
        "58": {
            "lo_mode_id": 9,
            "if_freq": -182116752.0,
            "latest": 98
        },
        "59": {
            "lo_mode_id": 10,
            "if_freq": -166987507.0,
            "latest": 89
        },
        "60": {
            "lo_mode_id": 11,
            "if_freq": -260855490.0,
            "latest": 90
        },
        "61": {
            "lo_mode_id": 7,
            "if_freq": -131770699.0,
            "latest": 86
        },
        "62": {
            "lo_mode_id": 8,
            "if_freq": -86467904.0,
            "latest": 87
        },
        "63": {
            "lo_mode_id": 1,
            "if_freq": -347122421,
            "latest": 91
        },
        "64": {
            "lo_mode_id": 1,
            "if_freq": 110501126,
            "latest": 94
        },
        "65": {
            "lo_mode_id": 7,
            "if_freq": -130770699.0,
            "latest": 96
        },
        "66": {
            "lo_mode_id": 8,
            "if_freq": -86351733.0,
            "latest": 97
        },
        "67": {
            "lo_mode_id": 10,
            "if_freq": -166786237.0,
            "latest": 99
        },
        "68": {
            "lo_mode_id": 11,
            "if_freq": -262855490.0,
            "latest": 100
        }
    },
    "if_cal": {
        "1": {
            "if_mode_id": 1,
            "gain": -0.013091400846378873,
            "phase": 0.07211645601220427,
            "temperature": 58.4375,
            "timestamp": 1728555011.625944,
            "method": "auto"
        },
        "2": {
            "if_mode_id": 2,
            "gain": -0.013224450358485044,
            "phase": 0.021501765971699588,
            "temperature": 58.4375,
            "timestamp": 1728555011.6275969,
            "method": "auto"
        },
        "3": {
            "if_mode_id": 3,
            "gain": -0.009848918715510807,
            "phase": -0.04218230748486979,
            "temperature": 58.4375,
            "timestamp": 1728555011.6294217,
            "method": "auto"
        },
        "4": {
            "if_mode_id": 4,
            "gain": -0.009971871368747833,
            "phase": -0.11220233758039787,
            "temperature": 58.4375,
            "timestamp": 1728555011.6312494,
            "method": "auto"
        },
        "5": {
            "if_mode_id": 5,
            "gain": -0.009851398558092004,
            "phase": -0.17592155656256014,
            "temperature": 58.4375,
            "timestamp": 1728555011.6330907,
            "method": "auto"
        },
        "6": {
            "if_mode_id": 6,
            "gain": 0.008738539009554671,
            "phase": 0.20917642727768634,
            "temperature": 59.5,
            "timestamp": 1728555085.4544985,
            "method": "auto"
        },
        "7": {
            "if_mode_id": 7,
            "gain": 0.007528385155430679,
            "phase": 0.21223393014263756,
            "temperature": 54.875,
            "timestamp": 1728555102.2554321,
            "method": "auto"
        },
        "8": {
            "if_mode_id": 8,
            "gain": -0.009320739852219618,
            "phase": 0.08978771195972685,
            "temperature": 53.375,
            "timestamp": 1728555120.422252,
            "method": "auto"
        },
        "9": {
            "if_mode_id": 9,
            "gain": 0.006239034457793947,
            "phase": -0.004418620892254321,
            "temperature": 51.0,
            "timestamp": 1728555137.2645822,
            "method": "auto"
        },
        "10": {
            "if_mode_id": 10,
            "gain": 0.0022756932993787155,
            "phase": -0.05814743852671666,
            "temperature": 56.0625,
            "timestamp": 1728555154.7983007,
            "method": "auto"
        },
        "11": {
            "if_mode_id": 11,
            "gain": -0.012053248083273876,
            "phase": 0.1731320298821973,
            "temperature": 58.1875,
            "timestamp": 1735648177.9273703,
            "method": "auto"
        },
        "12": {
            "if_mode_id": 12,
            "gain": -0.013417564170502112,
            "phase": 0.07847018696151886,
            "temperature": 58.1875,
            "timestamp": 1735648177.932299,
            "method": "auto"
        },
        "13": {
            "if_mode_id": 13,
            "gain": -0.010201682259959944,
            "phase": -0.028037982428851003,
            "temperature": 58.1875,
            "timestamp": 1735648177.9353213,
            "method": "auto"
        },
        "14": {
            "if_mode_id": 14,
            "gain": -0.010980923403882563,
            "phase": -0.1464476490533284,
            "temperature": 58.1875,
            "timestamp": 1735648177.93837,
            "method": "auto"
        },
        "15": {
            "if_mode_id": 15,
            "gain": -0.010711859009730373,
            "phase": -0.25783904283463377,
            "temperature": 58.1875,
            "timestamp": 1735648177.9414237,
            "method": "auto"
        },
        "16": {
            "if_mode_id": 16,
            "gain": 0.008847209361891581,
            "phase": 0.2010225085066961,
            "temperature": 59.1875,
            "timestamp": 1735648190.288345,
            "method": "auto"
        },
        "17": {
            "if_mode_id": 17,
            "gain": 0.007487346945166711,
            "phase": 0.20944839757873582,
            "temperature": 54.5,
            "timestamp": 1735648202.6697228,
            "method": "auto"
        },
        "18": {
            "if_mode_id": 18,
            "gain": -0.007849868459635945,
            "phase": 0.09403955584926979,
            "temperature": 52.6875,
            "timestamp": 1735648215.92626,
            "method": "auto"
        },
        "19": {
            "if_mode_id": 19,
            "gain": 0.004023108481110975,
            "phase": -0.0002391048509885753,
            "temperature": 50.5625,
            "timestamp": 1735648228.8183017,
            "method": "auto"
        },
        "20": {
            "if_mode_id": 20,
            "gain": 0.0023777357612614386,
            "phase": -0.05797094845610933,
            "temperature": 55.8125,
            "timestamp": 1735648241.2078938,
            "method": "auto"
        },
        "21": {
            "if_mode_id": 21,
            "gain": -0.010983257102578234,
            "phase": 0.18144591637034552,
            "temperature": 58.25,
            "timestamp": 1735803667.5103958,
            "method": "auto"
        },
        "22": {
            "if_mode_id": 22,
            "gain": -0.014532336813231865,
            "phase": 0.07900168492192232,
            "temperature": 58.25,
            "timestamp": 1735803667.5238276,
            "method": "auto"
        },
        "23": {
            "if_mode_id": 23,
            "gain": -0.010022457105159019,
            "phase": -0.028245286577958367,
            "temperature": 58.25,
            "timestamp": 1735803667.5298455,
            "method": "auto"
        },
        "24": {
            "if_mode_id": 24,
            "gain": -0.010334991278979307,
            "phase": -0.14778610978824788,
            "temperature": 58.25,
            "timestamp": 1735803667.534108,
            "method": "auto"
        },
        "25": {
            "if_mode_id": 25,
            "gain": -0.01108056514688013,
            "phase": -0.2600409753661867,
            "temperature": 58.25,
            "timestamp": 1735803667.5384324,
            "method": "auto"
        },
        "26": {
            "if_mode_id": 26,
            "gain": 0.009356550468795341,
            "phase": 0.20132461033879098,
            "temperature": 59.25,
            "timestamp": 1735803679.7723477,
            "method": "auto"
        },
        "27": {
            "if_mode_id": 27,
            "gain": 0.007465802578739985,
            "phase": 0.2091975735780571,
            "temperature": 54.5625,
            "timestamp": 1735803690.3664353,
            "method": "auto"
        },
        "28": {
            "if_mode_id": 28,
            "gain": -0.007870576228209825,
            "phase": 0.09486394971580278,
            "temperature": 52.875,
            "timestamp": 1735803702.2984161,
            "method": "auto"
        },
        "29": {
            "if_mode_id": 29,
            "gain": 0.0043486719426078955,
            "phase": -0.0007670856440765829,
            "temperature": 50.625,
            "timestamp": 1735803714.33266,
            "method": "auto"
        },
        "30": {
            "if_mode_id": 30,
            "gain": 0.00197869995697862,
            "phase": -0.0563752754282179,
            "temperature": 55.9375,
            "timestamp": 1735803726.8535078,
            "method": "auto"
        },
        "31": {
            "if_mode_id": 31,
            "gain": -0.012408116426414225,
            "phase": 0.179418112113136,
            "temperature": 58.375,
            "timestamp": 1736755867.3063846,
            "method": "auto"
        },
        "32": {
            "if_mode_id": 32,
            "gain": -0.014322763407558116,
            "phase": 0.07934141257832254,
            "temperature": 58.375,
            "timestamp": 1736755867.3161206,
            "method": "auto"
        },
        "33": {
            "if_mode_id": 33,
            "gain": -0.010024763399564136,
            "phase": -0.02821880163849229,
            "temperature": 58.375,
            "timestamp": 1736755867.3234472,
            "method": "auto"
        },
        "34": {
            "if_mode_id": 34,
            "gain": -0.010020706911412687,
            "phase": -0.14720544782507303,
            "temperature": 58.375,
            "timestamp": 1736755867.3296711,
            "method": "auto"
        },
        "35": {
            "if_mode_id": 35,
            "gain": -0.010402016014496368,
            "phase": -0.2595652624191123,
            "temperature": 58.375,
            "timestamp": 1736755867.3358593,
            "method": "auto"
        },
        "36": {
            "if_mode_id": 36,
            "gain": 0.008938237969771692,
            "phase": 0.2016787867667867,
            "temperature": 59.3125,
            "timestamp": 1736755879.5609589,
            "method": "auto"
        },
        "37": {
            "if_mode_id": 37,
            "gain": 0.007377755233342828,
            "phase": 0.2088471179087486,
            "temperature": 54.75,
            "timestamp": 1736755891.2022521,
            "method": "auto"
        },
        "38": {
            "if_mode_id": 38,
            "gain": -0.0077206570136303205,
            "phase": 0.09563390039707474,
            "temperature": 53.0,
            "timestamp": 1736755903.8299205,
            "method": "auto"
        },
        "39": {
            "if_mode_id": 39,
            "gain": 0.004344803224927576,
            "phase": -0.0004182728576128748,
            "temperature": 50.8125,
            "timestamp": 1736755915.6044066,
            "method": "auto"
        },
        "40": {
            "if_mode_id": 40,
            "gain": 0.00136594076663948,
            "phase": -0.05588777474623604,
            "temperature": 56.0625,
            "timestamp": 1736755927.4197302,
            "method": "auto"
        },
        "41": {
            "if_mode_id": 31,
            "gain": -0.012788423893055149,
            "phase": 0.179393288086814,
            "temperature": 58.375,
            "timestamp": 1736756013.494821,
            "method": "auto"
        },
        "42": {
            "if_mode_id": 32,
            "gain": -0.014459088649973043,
            "phase": 0.07891840762716994,
            "temperature": 58.375,
            "timestamp": 1736756013.5036297,
            "method": "auto"
        },
        "43": {
            "if_mode_id": 33,
            "gain": -0.010277054690114784,
            "phase": -0.02831094054516802,
            "temperature": 58.375,
            "timestamp": 1736756013.5081642,
            "method": "auto"
        },
        "44": {
            "if_mode_id": 34,
            "gain": -0.010281229919622001,
            "phase": -0.14809914536119687,
            "temperature": 58.375,
            "timestamp": 1736756013.5125928,
            "method": "auto"
        },
        "45": {
            "if_mode_id": 35,
            "gain": -0.010335315446692288,
            "phase": -0.26026011995922227,
            "temperature": 58.375,
            "timestamp": 1736756013.5169775,
            "method": "auto"
        },
        "46": {
            "if_mode_id": 36,
            "gain": 0.008955056764973043,
            "phase": 0.2013496146137511,
            "temperature": 59.3125,
            "timestamp": 1736756025.273616,
            "method": "auto"
        },
        "47": {
            "if_mode_id": 37,
            "gain": 0.007330685247376706,
            "phase": 0.20856447842364678,
            "temperature": 54.75,
            "timestamp": 1736756037.183737,
            "method": "auto"
        },
        "48": {
            "if_mode_id": 38,
            "gain": -0.007703635872581298,
            "phase": 0.0953672882403091,
            "temperature": 53.0625,
            "timestamp": 1736756049.2985508,
            "method": "auto"
        },
        "49": {
            "if_mode_id": 39,
            "gain": 0.004925473860079514,
            "phase": -0.00013647051916556668,
            "temperature": 50.75,
            "timestamp": 1736756061.9211457,
            "method": "auto"
        },
        "50": {
            "if_mode_id": 40,
            "gain": 0.001955839734327033,
            "phase": -0.05663867900770045,
            "temperature": 56.0625,
            "timestamp": 1736756075.12299,
            "method": "auto"
        },
        "51": {
            "if_mode_id": 41,
            "gain": -0.014698089540218458,
            "phase": 0.07180517943103841,
            "temperature": 58.4375,
            "timestamp": 1738929787.9716027,
            "method": "auto"
        },
        "52": {
            "if_mode_id": 42,
            "gain": -0.013853114131517174,
            "phase": 0.01814454162782596,
            "temperature": 58.4375,
            "timestamp": 1738929787.9835207,
            "method": "auto"
        },
        "53": {
            "if_mode_id": 43,
            "gain": -0.009886808346047677,
            "phase": -0.04399793849030137,
            "temperature": 58.4375,
            "timestamp": 1738929787.991417,
            "method": "auto"
        },
        "54": {
            "if_mode_id": 44,
            "gain": -0.0102362360615776,
            "phase": -0.11329875628457041,
            "temperature": 58.4375,
            "timestamp": 1738929787.9980817,
            "method": "auto"
        },
        "55": {
            "if_mode_id": 45,
            "gain": -0.009986408151844052,
            "phase": -0.17297542789769535,
            "temperature": 58.4375,
            "timestamp": 1738929788.004972,
            "method": "auto"
        },
        "56": {
            "if_mode_id": 46,
            "gain": 0.009219367335776133,
            "phase": 0.1971736820896466,
            "temperature": 59.375,
            "timestamp": 1738929800.5950882,
            "method": "auto"
        },
        "57": {
            "if_mode_id": 47,
            "gain": 0.007397933735368337,
            "phase": 0.2143090993475343,
            "temperature": 54.875,
            "timestamp": 1738929813.1038003,
            "method": "auto"
        },
        "58": {
            "if_mode_id": 48,
            "gain": -0.00750009571161962,
            "phase": 0.10374651039004956,
            "temperature": 53.0,
            "timestamp": 1738929825.7678988,
            "method": "auto"
        },
        "59": {
            "if_mode_id": 49,
            "gain": 0.0037869455072934094,
            "phase": 0.008294510268225617,
            "temperature": 50.9375,
            "timestamp": 1738929838.6851287,
            "method": "auto"
        },
        "60": {
            "if_mode_id": 50,
            "gain": 0.0019529657444985467,
            "phase": -0.050600928105500556,
            "temperature": 56.125,
            "timestamp": 1738929851.3297713,
            "method": "auto"
        },
        "61": {
            "if_mode_id": 41,
            "gain": -0.013001877582439555,
            "phase": 0.052908842208904905,
            "temperature": 58.75,
            "timestamp": 1739797483.1575181,
            "method": "auto"
        },
        "62": {
            "if_mode_id": 42,
            "gain": -0.014495995900851785,
            "phase": 0.00737817227713895,
            "temperature": 58.75,
            "timestamp": 1739797483.1666613,
            "method": "auto"
        },
        "63": {
            "if_mode_id": 43,
            "gain": -0.010146421222177342,
            "phase": -0.045841194829099645,
            "temperature": 58.75,
            "timestamp": 1739797483.1728706,
            "method": "auto"
        },
        "64": {
            "if_mode_id": 44,
            "gain": -0.00980754102226774,
            "phase": -0.1062614775900052,
            "temperature": 58.75,
            "timestamp": 1739797483.1786382,
            "method": "auto"
        },
        "65": {
            "if_mode_id": 45,
            "gain": -0.010402408452285242,
            "phase": -0.15967424600564514,
            "temperature": 58.75,
            "timestamp": 1739797483.1840122,
            "method": "auto"
        },
        "66": {
            "if_mode_id": 46,
            "gain": 0.009147643277619128,
            "phase": 0.21426065943756173,
            "temperature": 59.5,
            "timestamp": 1739797495.2332344,
            "method": "auto"
        },
        "67": {
            "if_mode_id": 47,
            "gain": 0.007121180800559294,
            "phase": 0.23642888503184892,
            "temperature": 55.125,
            "timestamp": 1739797508.2197912,
            "method": "auto"
        },
        "68": {
            "if_mode_id": 48,
            "gain": -0.007703792388612014,
            "phase": 0.11625481568606355,
            "temperature": 53.1875,
            "timestamp": 1739797520.5221164,
            "method": "auto"
        },
        "69": {
            "if_mode_id": 49,
            "gain": 0.004339522639624714,
            "phase": -0.00953399549362705,
            "temperature": 51.25,
            "timestamp": 1739797533.5190027,
            "method": "auto"
        },
        "70": {
            "if_mode_id": 50,
            "gain": 0.001955105804539338,
            "phase": -0.08474305648209661,
            "temperature": 56.5625,
            "timestamp": 1739797546.1801944,
            "method": "auto"
        },
        "71": {
            "if_mode_id": 51,
            "gain": -0.01335913512015952,
            "phase": 0.021793897559093237,
            "temperature": 58.9375,
            "timestamp": 1741767943.121983,
            "method": "auto"
        },
        "72": {
            "if_mode_id": 52,
            "gain": -0.009261733676849552,
            "phase": -0.022156295781705804,
            "temperature": 58.9375,
            "timestamp": 1741767943.1350965,
            "method": "auto"
        },
        "73": {
            "if_mode_id": 53,
            "gain": -0.006327858295936552,
            "phase": -0.07099317777691716,
            "temperature": 58.9375,
            "timestamp": 1741767943.144521,
            "method": "auto"
        },
        "74": {
            "if_mode_id": 54,
            "gain": -0.007255850043861226,
            "phase": -0.1294564407884772,
            "temperature": 58.9375,
            "timestamp": 1741767943.1533606,
            "method": "auto"
        },
        "75": {
            "if_mode_id": 55,
            "gain": -0.009285976709708111,
            "phase": -0.17625349318460612,
            "temperature": 58.9375,
            "timestamp": 1741767943.1616879,
            "method": "auto"
        },
        "76": {
            "if_mode_id": 56,
            "gain": 0.008642097063651545,
            "phase": 0.18812644095620792,
            "temperature": 58.625,
            "timestamp": 1741767955.6442502,
            "method": "auto"
        },
        "77": {
            "if_mode_id": 57,
            "gain": 0.0062766070038357625,
            "phase": 0.18653392347149836,
            "temperature": 59.375,
            "timestamp": 1741767968.2045748,
            "method": "auto"
        },
        "78": {
            "if_mode_id": 58,
            "gain": -0.004924630835695532,
            "phase": 0.032592017408777846,
            "temperature": 53.25,
            "timestamp": 1741767980.4988642,
            "method": "auto"
        },
        "79": {
            "if_mode_id": 59,
            "gain": 0.006495876130820661,
            "phase": -0.07260882697560497,
            "temperature": 56.0,
            "timestamp": 1741767993.1422906,
            "method": "auto"
        },
        "80": {
            "if_mode_id": 60,
            "gain": 0.0053048123857488555,
            "phase": -0.08493361413704781,
            "temperature": 55.375,
            "timestamp": 1741768006.248398,
            "method": "auto"
        },
        "81": {
            "if_mode_id": 51,
            "gain": -0.013321221364487578,
            "phase": -0.028084228999101398,
            "temperature": 57.9375,
            "timestamp": 1742194229.554777,
            "method": "auto"
        },
        "82": {
            "if_mode_id": 52,
            "gain": -0.008111193827263446,
            "phase": -0.05265099808953037,
            "temperature": 57.9375,
            "timestamp": 1742194229.565235,
            "method": "auto"
        },
        "83": {
            "if_mode_id": 53,
            "gain": -0.006125501085405496,
            "phase": -0.07841900589689248,
            "temperature": 57.9375,
            "timestamp": 1742194229.573395,
            "method": "auto"
        },
        "84": {
            "if_mode_id": 54,
            "gain": -0.006926396519426999,
            "phase": -0.10964426659100174,
            "temperature": 57.9375,
            "timestamp": 1742194229.5804265,
            "method": "auto"
        },
        "85": {
            "if_mode_id": 55,
            "gain": -0.008432832645888325,
            "phase": -0.13560303195267076,
            "temperature": 57.9375,
            "timestamp": 1742194229.587371,
            "method": "auto"
        },
        "86": {
            "if_mode_id": 61,
            "gain": 0.013082988529342856,
            "phase": 0.20634623043224812,
            "temperature": 58.3125,
            "timestamp": 1742194241.7600977,
            "method": "auto"
        },
        "87": {
            "if_mode_id": 62,
            "gain": 0.00849548790698124,
            "phase": 0.22096359798488885,
            "temperature": 59.3125,
            "timestamp": 1742194254.697392,
            "method": "auto"
        },
        "88": {
            "if_mode_id": 58,
            "gain": -0.004889271777698856,
            "phase": 0.04358383454496524,
            "temperature": 52.8125,
            "timestamp": 1742194267.7569358,
            "method": "auto"
        },
        "89": {
            "if_mode_id": 59,
            "gain": 0.005739163191738656,
            "phase": -0.07214654121801152,
            "temperature": 56.0625,
            "timestamp": 1742194280.0814462,
            "method": "auto"
        },
        "90": {
            "if_mode_id": 60,
            "gain": 0.005058438031349026,
            "phase": -0.044910071871562006,
            "temperature": 52.5,
            "timestamp": 1742194292.6292317,
            "method": "auto"
        },
        "91": {
            "if_mode_id": 63,
            "gain": -0.012551460355681946,
            "phase": -0.029208094060006445,
            "temperature": 58.0625,
            "timestamp": 1742278003.8589308,
            "method": "auto"
        },
        "92": {
            "if_mode_id": 52,
            "gain": -0.009623345935209417,
            "phase": -0.052824695319096386,
            "temperature": 58.0625,
            "timestamp": 1742278003.8683727,
            "method": "auto"
        },
        "93": {
            "if_mode_id": 53,
            "gain": -0.006721249703223474,
            "phase": -0.0788184102944955,
            "temperature": 58.0625,
            "timestamp": 1742278003.8761106,
            "method": "auto"
        },
        "94": {
            "if_mode_id": 64,
            "gain": -0.006078096861881632,
            "phase": -0.10971942542508546,
            "temperature": 58.0625,
            "timestamp": 1742278003.8860245,
            "method": "auto"
        },
        "95": {
            "if_mode_id": 55,
            "gain": -0.009463289708117334,
            "phase": -0.1360634745790293,
            "temperature": 58.0625,
            "timestamp": 1742278003.8933153,
            "method": "auto"
        },
        "96": {
            "if_mode_id": 65,
            "gain": 0.013112672830615025,
            "phase": 0.2061823771969427,
            "temperature": 58.375,
            "timestamp": 1742278016.71456,
            "method": "auto"
        },
        "97": {
            "if_mode_id": 66,
            "gain": 0.008702700288287263,
            "phase": 0.2211786475159036,
            "temperature": 59.375,
            "timestamp": 1742278029.300087,
            "method": "auto"
        },
        "98": {
            "if_mode_id": 58,
            "gain": -0.004606667571594973,
            "phase": 0.044668586691380116,
            "temperature": 52.875,
            "timestamp": 1742278042.2925947,
            "method": "auto"
        },
        "99": {
            "if_mode_id": 67,
            "gain": 0.0051050752877308935,
            "phase": -0.07176605342601898,
            "temperature": 56.0625,
            "timestamp": 1742278055.4802864,
            "method": "auto"
        },
        "100": {
            "if_mode_id": 68,
            "gain": 0.005302373616283166,
            "phase": -0.04401073306104779,
            "temperature": 52.625,
            "timestamp": 1742278069.162328,
            "method": "auto"
        }
    }
}