{
    "nqubits": 11,
    "settings": {
        "nshots": 2048,
        "relaxation_time": 100000
    },
    "qubits": [
        "A1",
        "A2",
        "A3",
        "A4",
        "A5",
        "A6",
        "D1",
        "D2",
        "D3",
        "D4",
        "D5"
    ],
    "topology": [
        ["A1", "A2"],
        ["A1", "A3"],
        ["A1", "D5"],
        ["A2", "A4"],
        ["A3", "A4"],
        ["A2", "A6"],
        ["A3", "D4"],
        ["A4", "A5"],
        ["A6", "D3"],
        ["D1", "D2"],
        ["D1", "D3"],
        ["D2", "D4"],
        ["D3", "D4"],
        ["D4", "D5"]
    ],
    "instruments": {
        "qm": {
            "bounds": {
                "waveforms": 40000,
                "readout": 30,
                "instructions": 1000000
            }
        },
        "octave4": {
            "o1": {
                "lo_frequency": 7500000000,
                "gain": 0
            },
            "o2": {
                "lo_frequency": 4900000000,
                "gain": 0
            },
            "o4": {
                "lo_frequency": 5700000000,
                "gain": 0
            },
            "i1": {
                "lo_frequency": 7500000000
            }
        },
        "octave5": {
            "o1": {
                "lo_frequency": 7500000000,
                "gain": 0
            },
            "o2": {
                "lo_frequency": 4900000000,
                "gain": 0
            },
            "o4": {
                "lo_frequency": 5700000000,
                "gain": 0
            },
            "i1": {
                "lo_frequency": 7500000000
            }
        },
        "octave6": {
            "o2": {
                "lo_frequency": 5700000000,
                "gain": 0
            },
            "o4": {
                "lo_frequency": 6500000000,
                "gain": 0
            }
        }
    },
    "native_gates": {
        "single_qubit": {
            "\"A1\"": {
                "RX": {
                    "duration": 40,
                    "amplitude": 0.05,
                    "shape": "Gaussian(5)",
                    "frequency": 4900000000,
                    "relative_start": 0,
                    "phase": 0,
                    "type": "qd"
                },
                "RX12": {
                    "duration": 40,
                    "amplitude": 0.05,
                    "shape": "Gaussian(5)",
                    "frequency": 4900000000,
                    "relative_start": 0,
                    "phase": 0.0,
                    "type": "qd"
                },
                "MZ": {
                    "duration": 2000,
                    "amplitude": 0.005,
                    "shape": "Rectangular()",
                    "frequency": 7190000000,
                    "relative_start": 0,
                    "phase": 0,
                    "type": "ro"
                }
            },
            "\"A2\"": {
                "RX": {
                    "duration": 40,
                    "amplitude": 0.05,
                    "shape": "Gaussian(5)",
                    "frequency": 5700000000,
                    "relative_start": 0,
                    "phase": 0,
                    "type": "qd"
                },
                "RX12": {
                    "duration": 40,
                    "amplitude": 0.05,
                    "shape": "Gaussian(5)",
                    "frequency": 5700000000,
                    "relative_start": 0,
                    "phase": 0.0,
                    "type": "qd"
                },
                "MZ": {
                    "duration": 2000,
                    "amplitude": 0.005,
                    "shape": "Rectangular()",
                    "frequency": 7440000000,
                    "relative_start": 0,
                    "phase": 0,
                    "type": "ro"
                }
            },
            "\"A3\"": {
                "RX": {
                    "duration": 40,
                    "amplitude": 0.05,
                    "shape": "Gaussian(5)",
                    "frequency": 5700000000,
                    "relative_start": 0,
                    "phase": 0,
                    "type": "qd"
                },
                "RX12": {
                    "duration": 40,
                    "amplitude": 0.05,
                    "shape": "Gaussian(5)",
                    "frequency": 5700000000,
                    "relative_start": 0,
                    "phase": 0.0,
                    "type": "qd"
                },
                "MZ": {
                    "duration": 2000,
                    "amplitude": 0.005,
                    "shape": "Rectangular()",
                    "frequency": 7560000000,
                    "relative_start": 0,
                    "phase": 0,
                    "type": "ro"
                }
            },
            "\"A4\"": {
                "RX": {
                    "duration": 40,
                    "amplitude": 0.05,
                    "shape": "Gaussian(5)",
                    "frequency": 4900000000,
                    "relative_start": 0,
                    "phase": 0,
                    "type": "qd"
                },
                "RX12": {
                    "duration": 40,
                    "amplitude": 0.05,
                    "shape": "Gaussian(5)",
                    "frequency": 4900000000,
                    "relative_start": 0,
                    "phase": 0.0,
                    "type": "qd"
                },
                "MZ": {
                    "duration": 2000,
                    "amplitude": 0.005,
                    "shape": "Rectangular()",
                    "frequency": 7320000000,
                    "relative_start": 0,
                    "phase": 0,
                    "type": "ro"
                }
            },
            "\"A5\"": {
                "RX": {
                    "duration": 40,
                    "amplitude": 0.05,
                    "shape": "Gaussian(5)",
                    "frequency": 5700000000,
                    "relative_start": 0,
                    "phase": 0,
                    "type": "qd"
                },
                "RX12": {
                    "duration": 40,
                    "amplitude": 0.05,
                    "shape": "Gaussian(5)",
                    "frequency": 5700000000,
                    "relative_start": 0,
                    "phase": 0.0,
                    "type": "qd"
                },
                "MZ": {
                    "duration": 2000,
                    "amplitude": 0.005,
                    "shape": "Rectangular()",
                    "frequency": 7680000000,
                    "relative_start": 0,
                    "phase": 0,
                    "type": "ro"
                }
            },
            "\"A6\"": {
                "RX": {
                    "duration": 40,
                    "amplitude": 0.05,
                    "shape": "Gaussian(5)",
                    "frequency": 6500000000,
                    "relative_start": 0,
                    "phase": 0,
                    "type": "qd"
                },
                "RX12": {
                    "duration": 40,
                    "amplitude": 0.05,
                    "shape": "Gaussian(5)",
                    "frequency": 6500000000,
                    "relative_start": 0,
                    "phase": 0.0,
                    "type": "qd"
                },
                "MZ": {
                    "duration": 2000,
                    "amplitude": 0.005,
                    "shape": "Rectangular()",
                    "frequency": 7800000000,
                    "relative_start": 0,
                    "phase": 0,
                    "type": "ro"
                }
            },
            "\"D1\"": {
                "RX": {
                    "duration": 40,
                    "amplitude": 0.05,
                    "shape": "Gaussian(5)",
                    "frequency": 4900000000,
                    "relative_start": 0,
                    "phase": 0,
                    "type": "qd"
                },
                "RX12": {
                    "duration": 40,
                    "amplitude": 0.05,
                    "shape": "Gaussian(5)",
                    "frequency": 4900000000,
                    "relative_start": 0,
                    "phase": 0.0,
                    "type": "qd"
                },
                "MZ": {
                    "duration": 2000,
                    "amplitude": 0.005,
                    "shape": "Rectangular()",
                    "frequency": 7200000000,
                    "relative_start": 0,
                    "phase": 0,
                    "type": "ro"
                }
            },
            "\"D2\"": {
                "RX": {
                    "duration": 40,
                    "amplitude": 0.05,
                    "shape": "Gaussian(5)",
                    "frequency": 5700000000,
                    "relative_start": 0,
                    "phase": 0,
                    "type": "qd"
                },
                "RX12": {
                    "duration": 40,
                    "amplitude": 0.05,
                    "shape": "Gaussian(5)",
                    "frequency": 5700000000,
                    "relative_start": 0,
                    "phase": 0.0,
                    "type": "qd"
                },
                "MZ": {
                    "duration": 2000,
                    "amplitude": 0.005,
                    "shape": "Rectangular()",
                    "frequency": 7440000000,
                    "relative_start": 0,
                    "phase": 0,
                    "type": "ro"
                }
            },
            "\"D3\"": {
                "RX": {
                    "duration": 40,
                    "amplitude": 0.05,
                    "shape": "Gaussian(5)",
                    "frequency": 5700000000,
                    "relative_start": 0,
                    "phase": 0,
                    "type": "qd"
                },
                "RX12": {
                    "duration": 40,
                    "amplitude": 0.05,
                    "shape": "Gaussian(5)",
                    "frequency": 5700000000,
                    "relative_start": 0,
                    "phase": 0.0,
                    "type": "qd"
                },
                "MZ": {
                    "duration": 2000,
                    "amplitude": 0.005,
                    "shape": "Rectangular()",
                    "frequency": 7560000000,
                    "relative_start": 0,
                    "phase": 0,
                    "type": "ro"
                }
            },
            "\"D4\"": {
                "RX": {
                    "duration": 40,
                    "amplitude": 0.05,
                    "shape": "Gaussian(5)",
                    "frequency": 6500000000,
                    "relative_start": 0,
                    "phase": 0,
                    "type": "qd"
                },
                "RX12": {
                    "duration": 40,
                    "amplitude": 0.05,
                    "shape": "Gaussian(5)",
                    "frequency": 6500000000,
                    "relative_start": 0,
                    "phase": 0.0,
                    "type": "qd"
                },
                "MZ": {
                    "duration": 2000,
                    "amplitude": 0.005,
                    "shape": "Rectangular()",
                    "frequency": 7800000000,
                    "relative_start": 0,
                    "phase": 0,
                    "type": "ro"
                }
            },
            "\"D5\"": {
                "RX": {
                    "duration": 40,
                    "amplitude": 0.05,
                    "shape": "Gaussian(5)",
                    "frequency": 5700000000,
                    "relative_start": 0,
                    "phase": 0,
                    "type": "qd"
                },
                "RX12": {
                    "duration": 40,
                    "amplitude": 0.05,
                    "shape": "Gaussian(5)",
                    "frequency": 5700000000,
                    "relative_start": 0,
                    "phase": 0.0,
                    "type": "qd"
                },
                "MZ": {
                    "duration": 2000,
                    "amplitude": 0.005,
                    "shape": "Rectangular()",
                    "frequency": 7680000000,
                    "relative_start": 0,
                    "phase": 0,
                    "type": "ro"
                }
            }
        }
    },
    "characterization": {
        "single_qubit": {
            "\"A1\"": {},
            "\"A2\"": {},
            "\"A3\"": {},
            "\"A4\"": {},
            "\"A5\"": {},
            "\"A6\"": {},
            "\"D1\"": {},
            "\"D2\"": {},
            "\"D3\"": {},
            "\"D4\"": {},
            "\"D5\"": {}
    }
}
}
