{
  "nqubits": 1,
  "settings": {
    "nshots": 4024,
    "relaxation_time": 100000
  },
  "topology": [],
  "qubits": [
    0
  ],
  "native_gates": {
    "single_qubit": {
      "0": {
        "RX": {
          "duration": 80,
          "amplitude": 0.1408,
          "shape": "Gaussian(5)",
          "frequency": 5796280570,
          "relative_start": 0,
          "phase": 0,
          "type": "qd"
        },
        "MZ": {
          "duration": 2000,
          "amplitude": 0.04,
          "shape": "Rectangular()",
          "frequency": 7292077169,
          "relative_start": 0,
          "phase": 0,
          "type": "ro"
        }
      }
    },
    "two_qubits": {}
  },

  "characterization": {
    "single_qubit": {
      "0": {
        "bare_resonator_frequency": 7286806886,
        "readout_frequency": 7292077169,
        "drive_frequency": 5796280570,
        "anharmonicity": 0,
        "sweetspot": 0,
        "asymmetry": 0,
        "Ec": 0,
        "g": 0,
        "assignment_fidelity": 0.947,
        "readout_fidelity": 0.895,
        "effective_temperature": 0,
        "peak_voltage": 0,
        "pi_pulse_amplitude": 0.2196,
        "T1": 9719,
        "T2": 9283,
        "T2_spin_echo": 0,
        "state0_voltage": 0,
        "state1_voltage": 0,
        "mean_gnd_states": [
          0,
          0
        ],
        "mean_exc_states": [
          0,
          0
        ],
        "threshold": -0.175273,
        "iq_angle": -0.5,
        "mixer_drive_g": 0,
        "mixer_drive_phi": 0,
        "mixer_readout_g": 0,
        "mixer_readout_phi": 0
      }
    }
  }
}